Metadata-Version: 2.1
Name: complex-curve-fit-gui
Version: 1.1.5
Summary: GUI for lmfit using matplotlib
Home-page: https://github.com/boakyeni/data-visualization-and-curve-fitting
Author: Kojo Nimako
Author-email: boakyeni@usc.edu
License: MIT
Classifier: License :: OSI Approved :: MIT License
Classifier: Programming Language :: Python :: 3
Classifier: Operating System :: OS Independent
Requires-Python: >=3.7, <4
